tomodachi_testcontainers/__init__.py
tomodachi_testcontainers/assertions.py
tomodachi_testcontainers/async_probes.py
tomodachi_testcontainers/clients/__init__.py
tomodachi_testcontainers/clients/snssqs.py
tomodachi_testcontainers/containers/__init__.py
tomodachi_testcontainers/containers/common/__init__.py
tomodachi_testcontainers/containers/common/container.py
tomodachi_testcontainers/containers/common/database.py
tomodachi_testcontainers/containers/common/image.py
tomodachi_testcontainers/containers/common/web.py
tomodachi_testcontainers/containers/dynamodb_admin.py
tomodachi_testcontainers/containers/localstack.py
tomodachi_testcontainers/containers/minio.py
tomodachi_testcontainers/containers/moto.py
tomodachi_testcontainers/containers/mysql.py
tomodachi_testcontainers/containers/postgres.py
tomodachi_testcontainers/containers/sftp.py
tomodachi_testcontainers/containers/tomodachi.py
tomodachi_testcontainers/containers/wiremock.py
tomodachi_testcontainers/fixtures/__init__.py
tomodachi_testcontainers/fixtures/containers.py
tomodachi_testcontainers/fixtures/localstack.py
tomodachi_testcontainers/fixtures/minio.py
tomodachi_testcontainers/fixtures/moto.py
tomodachi_testcontainers/fixtures/mysql.py
tomodachi_testcontainers/fixtures/postgres.py
tomodachi_testcontainers/fixtures/sftp.py
tomodachi_testcontainers/fixtures/wiremock.py
tomodachi_testcontainers/py.typed
tomodachi_testcontainers/utils.py
tomodachi_testcontainers-1.2.3.dist-info/LICENSE
tomodachi_testcontainers-1.2.3.dist-info/METADATA
tomodachi_testcontainers-1.2.3.dist-info/WHEEL
tomodachi_testcontainers-1.2.3.dist-info/entry_points.txt
tomodachi_testcontainers-1.2.3.dist-info/RECORD
