Metadata-Version: 2.1
Name: tomodachi-testcontainers
Version: 1.2.3
Summary: Collection of Testcontainers, pytest fixtures and test clients for end-to-end/integration testing for Python Tomodachi framework. A great starting point to learn more about Testcontainers and necessity of integration testing.
Home-page: https://github.com/filipsnastins/tomodachi-testcontainers
License: MIT
Author: Filips Nastins
Author-email: nastinsfilips@gmail.com
Requires-Python: >=3.9,<4.0
Classifier: License :: OSI Approved :: MIT License
Classifier: Programming Language :: Python :: 3
Classifier: Programming Language :: Python :: 3.9
Classifier: Programming Language :: Python :: 3.10
Classifier: Programming Language :: Python :: 3.11
Classifier: Programming Language :: Python :: 3.12
Provides-Extra: db
Provides-Extra: mysql
Provides-Extra: postgres
Provides-Extra: sftp
Provides-Extra: wiremock
Requires-Dist: aiobotocore (>=2.4.2,<3.0.0)
Requires-Dist: asyncssh (>=2.13.2,<3.0.0) ; extra == "sftp"
Requires-Dist: cryptography (>=41,<44) ; extra == "mysql"
Requires-Dist: protobuf (>=4,<6)
Requires-Dist: psycopg (>=3.1.18,<4.0.0) ; extra == "postgres"
Requires-Dist: pymysql (>=1.1.0,<2.0.0) ; extra == "mysql"
Requires-Dist: pytest (>=7.1.2,<9.0.0)
Requires-Dist: pytest-asyncio (>=0.24.0,<0.25.0)
Requires-Dist: requests (>=2.31.0,<3.0.0)
Requires-Dist: shortuuid (>=1.0.11,<2.0.0)
Requires-Dist: sqlalchemy (>=1.3,<3) ; extra == "db" or extra == "mysql" or extra == "postgres"
Requires-Dist: tenacity (>=8.2.2,<10.0.0)
Requires-Dist: testcontainers (>=4.4.1,<5.0.0)
Requires-Dist: types-aiobotocore[dynamodb,iam,lambda,s3,sns,sqs,ssm] (>=2.4.2,<3.0.0)
Requires-Dist: wiremock (>=2.6.1,<3.0.0) ; extra == "wiremock"
Project-URL: Repository, https://github.com/filipsnastins/tomodachi-testcontainers
